[{"memberId":"654015811565","bookId":"10001","borrowDate":"16-10-2024","tillDate":"16-11-2024","returnDate":"18-10-2024","dues":0,"paid":true,"returned":false},{"memberId":"123456789","bookId":"21","borrowDate":"07-12-24","tillDate":"07-01-25","returnDate":"07-12-2024","dues":0,"paid":true,"returned":true},{"memberId":"123456789","bookId":"21","borrowDate":"07-12-24","tillDate":"07-01-25","returnDate":"07-12-2024","dues":0,"paid":true,"returned":true},{"memberId":"123456789","bookId":"4242","borrowDate":"07-12-24","tillDate":"07-01-25","returnDate":"07-12-2024","dues":0,"paid":true,"returned":true}]